.DS_Store
pyungo/__init__.py
pyungo/core.py
pyungo/data.py
pyungo/errors.py
pyungo/io.py
pyungo/utils.py
pyungo-0.9.0.dist-info/LICENSE.txt
pyungo-0.9.0.dist-info/METADATA
pyungo-0.9.0.dist-info/WHEEL
pyungo-0.9.0.dist-info/top_level.txt
pyungo-0.9.0.dist-info/RECORD
