Metadata-Version: 2.1
Name: pyungo
Version: 0.9.0
Summary: Function dependencies resolution and execution
Home-page: https://github.com/cedricleroy/pyungo
Author: Cedric Leroy
Author-email: cedie73@hotmail.fr
License: MIT
Keywords: dag workflow function dependency
Platform: UNKNOWN
Classifier: Development Status :: 3 - Alpha
Classifier: Intended Audience :: Developers
Classifier: License :: OSI Approved :: MIT License
Classifier: Programming Language :: Python :: 3
Classifier: Programming Language :: Python :: 3.6
Classifier: Programming Language :: Python :: 3.7
Classifier: Programming Language :: Python :: 3.8
